{
  "meta": {
    "updated": "2025-11-20T19:55:00Z",
    "totalPrograms": 8,
    "categories": ["Funding", "LiDAR", "Space Systems", "Platform"]
  },
  "programs": {
    "funding": [
      {
        "id": "usgs-100",
        "title": "USGS GPSC Subcontracting",
        "agency": "USGS",
        "category": "Funding",
        "pillar": "Federal",
        "value": "$850,000,000",
        "valueUSD": 850000000,
        "deadline": "2025-12-15",
        "daysUntil": 24,
        "urgency": "urgent",
        "nextAction": "Prime Outreach",
        "description": "USGS Government-wide contract for geospatial services",
        "link": "https://sam.gov/opp/8c3a5e5f1c8b4d3ea9f0c1b2d3e4f5a6/view",
        "agencyLink": "https://www.usgs.gov/",
        "budgetSourceLink": "https://www.usgs.gov/about/organization/science-support/budget-and-performance"
      },
      {
        "id": "usgs-107",
        "title": "USGS 3DEP LiDAR Acquisition 2026",
        "agency": "USGS",
        "category": "Funding",
        "pillar": "Federal",
        "value": "$217,000,000",
        "valueUSD": 217000000,
        "deadline": "2025-12-15",
        "daysUntil": 28,
        "urgency": "urgent",
        "nextAction": "Submit Demo Brief",
        "description": "3D Elevation Program LiDAR data acquisition",
        "link": "https://sam.gov/opp/3dep2026/view",
        "agencyLink": "https://www.usgs.gov/",
        "budgetSourceLink": "https://www.usgs.gov/core-science-systems/ngp/3dep"
      },
      {
        "id": "nasa-773",
        "title": "NASA ROSES Omnibus Earth Observation",
        "agency": "NASA",
        "category": "Funding",
        "pillar": "Federal",
        "value": "$50,000,000",
        "valueUSD": 50000000,
        "deadline": "2026-03-01",
        "daysUntil": 120,
        "urgency": "future",
        "nextAction": "Proposal Dev",
        "description": "Research Opportunities in Space and Earth Sciences",
        "link": "https://science.nasa.gov/researchers/solicitations/roses-2025/",
        "agencyLink": "https://www.nasa.gov/",
        "budgetSourceLink": "https://science.nasa.gov/earth-science/earth-science-data/budget/"
      }
    ],
    "lidar": [
      {
        "id": "usgs-107",
        "title": "USGS 3DEP LiDAR Acquisition 2026",
        "agency": "USGS",
        "category": "LiDAR",
        "pillar": "Federal",
        "value": "$217,000,000",
        "valueUSD": 217000000,
        "deadline": "2025-12-15",
        "daysUntil": 28,
        "urgency": "urgent",
        "nextAction": "Submit Demo Brief",
        "description": "3D Elevation Program LiDAR data acquisition",
        "link": "https://sam.gov/opp/3dep2026/view",
        "agencyLink": "https://www.usgs.gov/",
        "budgetSourceLink": "https://www.usgs.gov/core-science-systems/ngp/3dep"
      },
      {
        "id": "diu-438",
        "title": "DIU Spaceborne LiDAR BAA",
        "agency": "DIU",
        "category": "LiDAR",
        "pillar": "Federal",
        "value": "$10,000,000",
        "valueUSD": 10000000,
        "deadline": "2025-12-01",
        "daysUntil": 15,
        "urgency": "urgent",
        "nextAction": "Submit Whitepaper",
        "description": "Broad Agency Announcement for spaceborne LiDAR technology",
        "link": "https://www.diu.mil/solicitations/spaceborne-lidar",
        "agencyLink": "https://www.diu.mil/",
        "budgetSourceLink": "https://www.diu.mil/latest/diu-fiscal-year-2025-budget"
      },
      {
        "id": "fl-gio-285",
        "title": "Florida Seafloor Mapping",
        "agency": "Florida GIO",
        "category": "LiDAR",
        "pillar": "Federal",
        "value": "$10,000,000",
        "valueUSD": 10000000,
        "deadline": "2025-12-31",
        "daysUntil": 40,
        "urgency": "near",
        "nextAction": "Teaming Agreement",
        "description": "Bathymetric LiDAR for seafloor mapping",
        "link": "https://floridagio.gov/seafloor-mapping-rfp",
        "agencyLink": "https://floridagio.gov/",
        "budgetSourceLink": "https://floridagio.gov/about/funding/"
      }
    ],
    "spaceSystems": [
      {
        "id": "dod/diu-928",
        "title": "DIU — Project DRM-3 (Alternative PNT)",
        "agency": "DIU",
        "category": "Space Systems",
        "pillar": "Federal",
        "value": "$5,000,000",
        "valueUSD": 5000000,
        "deadline": "2025-11-16",
        "daysUntil": -5,
        "urgency": "urgent",
        "nextAction": "Submit Demo Brief",
        "description": "Alternative Position, Navigation, and Timing systems",
        "link": "https://www.diu.mil/solicitations/alternative-pnt",
        "agencyLink": "https://www.diu.mil/",
        "budgetSourceLink": "https://www.diu.mil/latest/diu-fiscal-year-2025-budget"
      },
      {
        "id": "nasa-488",
        "title": "NASA ROSES-2025 Omnibus",
        "agency": "NASA",
        "category": "Space Systems",
        "pillar": "Federal",
        "value": "$5,000,000",
        "valueUSD": 5000000,
        "deadline": "2026-12-31",
        "daysUntil": 405,
        "urgency": "future",
        "nextAction": "Proposal Dev",
        "description": "Research opportunities for space-based systems",
        "link": "https://science.nasa.gov/researchers/solicitations/roses-2025/",
        "agencyLink": "https://www.nasa.gov/",
        "budgetSourceLink": "https://science.nasa.gov/earth-science/earth-science-data/budget/"
      }
    ],
    "platform": [
      {
        "id": "esa-161",
        "title": "ESA Digital Twin Earth Platform",
        "agency": "ESA",
        "category": "Platform",
        "pillar": "Federal",
        "value": "$8,000,000",
        "valueUSD": 8000000,
        "deadline": "2026-01-20",
        "daysUntil": 45,
        "urgency": "near",
        "nextAction": "Consortium Lead",
        "description": "Digital twin platform for Earth observation",
        "link": "https://www.esa.int/Applications/Observing_the_Earth/Digital_Twin_Earth",
        "agencyLink": "https://www.esa.int/",
        "budgetSourceLink": "https://www.esa.int/About_Us/Corporate_news/Funding"
      },
      {
        "id": "fl-gio-285",
        "title": "Florida Seafloor Mapping",
        "agency": "Florida GIO",
        "category": "Platform",
        "pillar": "Federal",
        "value": "$10,000,000",
        "valueUSD": 10000000,
        "deadline": "2025-12-31",
        "daysUntil": 40,
        "urgency": "near",
        "nextAction": "Teaming Agreement",
        "description": "Platform for seafloor data management",
        "link": "https://floridagio.gov/seafloor-mapping-rfp",
        "agencyLink": "https://floridagio.gov/",
        "budgetSourceLink": "https://floridagio.gov/about/funding/"
      }
    ]
  }
}
